{
    "paciente": "",
    "intentos": [
        {
            "intento": 1,
            "tiempo_ms": 3319.12,
            "exito": true
        },
        {
            "intento": 2,
            "tiempo_ms": 3282.4,
            "exito": true
        },
        {
            "intento": 3,
            "tiempo_ms": 1600.3,
            "exito": true
        },
        {
            "intento": 4,
            "tiempo_ms": 3381.36,
            "exito": true
        },
        {
            "intento": 5,
            "tiempo_ms": 2782.58,
            "exito": true
        },
        {
            "intento": 6,
            "tiempo_ms": 2366.01,
            "exito": true
        },
        {
            "intento": 7,
            "tiempo_ms": 2797.87,
            "exito": true
        },
        {
            "intento": 8,
            "tiempo_ms": 3171.13,
            "exito": true
        },
        {
            "intento": 8,
            "tiempo_ms": 5615.33,
            "exito": true
        },
        {
            "intento": 8,
            "tiempo_ms": 6882.54,
            "exito": false
        }
    ]
}